{
  "project_info": {
    "project_number": "239467616339",
    "project_id": "eventos-teste-16301",
    "storage_bucket": "eventos-teste-16301.firebasestorage.app"
  },
  "client": [
    {
      "client_info": {
        "mobilesdk_app_id": "1:239467616339:android:36cc2a854899db00e74ea6",
        "android_client_info": {
          "package_name": "com.example.habit_tracker"
        }
      },
      "oauth_client": [],
      "api_key": [
        {
          "current_key": "AIzaSyBNSHIMVRyVOIe3eFijZEF02_DCCIeLTsU"
        }
      ],
      "services": {
        "appinvite_service": {
          "other_platform_oauth_client": []
        }
      }
    },
    {
      "client_info": {
        "mobilesdk_app_id": "1:239467616339:android:fef4da9858d06af5e74ea6",
        "android_client_info": {
          "package_name": "com.outsystemscloud.personalk7njwyvf.Events1"
        }
      },
      "oauth_client": [],
      "api_key": [
        {
          "current_key": "AIzaSyBNSHIMVRyVOIe3eFijZEF02_DCCIeLTsU"
        }
      ],
      "services": {
        "appinvite_service": {
          "other_platform_oauth_client": []
        }
      }
    }
  ],
  "configuration_version": "1"
}